django_pgcli/__init__.py
django_pgcli-1.0.1.dist-info/AUTHORS.md
django_pgcli-1.0.1.dist-info/LICENSE
django_pgcli-1.0.1.dist-info/METADATA
django_pgcli-1.0.1.dist-info/WHEEL
django_pgcli-1.0.1.dist-info/top_level.txt
django_pgcli-1.0.1.dist-info/RECORD
