Metadata-Version: 2.1
Name: django-pgcli
Version: 1.0.1
Summary: Database runtime for Django that replaces psql with pgcli.
Home-page: https://github.com/ashchristopher/django-pgcli
Author: Ash Christopher
Author-email: ash.christopher@gmail.com
License: BSD
Keywords: django pgcli postgres database
Platform: UNKNOWN
Classifier: Development Status :: 5 - Production/Stable
Classifier: Intended Audience :: Developers
Classifier: License :: OSI Approved :: BSD License
Classifier: Natural Language :: English
Classifier: Programming Language :: Python :: 3.6
Classifier: Programming Language :: Python :: 3.7
Classifier: Programming Language :: Python :: 3.8
Requires-Dist: psycopg2
Requires-Dist: pgcli
Requires-Dist: Django (>=2.2.13)
